nise/VERSION
nise/__init__.py
nise/_converters.py
nise/_library.py
nise/_library_interpreter.py
nise/_library_singleton.py
nise/_visatype.py
nise/enums.py
nise/errors.py
nise/session.py
nise-1.4.9.dist-info/METADATA
nise-1.4.9.dist-info/WHEEL
nise-1.4.9.dist-info/top_level.txt
nise-1.4.9.dist-info/zip-safe
nise-1.4.9.dist-info/RECORD
